restrictedsessions/__init__.py
restrictedsessions/middleware.py
django_restricted_sessions-0.4.0.dist-info/AUTHORS.rst
django_restricted_sessions-0.4.0.dist-info/LICENSE
django_restricted_sessions-0.4.0.dist-info/METADATA
django_restricted_sessions-0.4.0.dist-info/WHEEL
django_restricted_sessions-0.4.0.dist-info/top_level.txt
django_restricted_sessions-0.4.0.dist-info/RECORD
