Metadata-Version: 2.1
Name: django-restricted-sessions
Version: 0.4.0
Summary: Restrict Django sessions to IP and/or user agent.
Home-page: https://github.com/mxsasha/django-restricted-sessions
Author: django-restricted-sessions
Author-email: github@mxsasha.eu
License: BSD
Keywords: django-restricted-sessions
Classifier: Development Status :: 4 - Beta
Classifier: Framework :: Django
Classifier: Framework :: Django :: 3.2
Classifier: Framework :: Django :: 4.0
Classifier: Intended Audience :: Developers
Classifier: License :: OSI Approved :: BSD License
Classifier: Natural Language :: English
Classifier: Programming Language :: Python :: 3.6
Classifier: Programming Language :: Python :: 3.7
Classifier: Programming Language :: Python :: 3.8
Classifier: Programming Language :: Python :: 3.9
Classifier: Programming Language :: Python :: 3.10
License-File: LICENSE
License-File: AUTHORS.rst
Requires-Dist: netaddr (>=0.7.10)
